mlbnb-0.1.9.dist-info/METADATA
mlbnb-0.1.9.dist-info/WHEEL
mlbnb-0.1.9.dist-info/entry_points.txt
mlbnb-0.1.9.dist-info/licenses/LICENSE
mlbnb/__init__.py
mlbnb/cache.py
mlbnb/checkpoint.py
mlbnb/checksum.py
mlbnb/early_stopper.py
mlbnb/examples.py
mlbnb/file.py
mlbnb/iter.py
mlbnb/labelled_array.py
mlbnb/metric_logger.py
mlbnb/namegen.py
mlbnb/paths.py
mlbnb/profiler.py
mlbnb/rand.py
mlbnb/types.py
mlbnb-0.1.9.dist-info/RECORD
