Metadata-Version: 2.1
Name: mlbnb
Version: 0.1.9
Summary: Machine learning bread and butter - a collection of basic deep learning tools
Author-Email: Jonas Scholz <jonas.scholz123@gmail.com>
License: MIT
Requires-Python: >=3.11
Requires-Dist: torch>=2.9.1
Requires-Dist: numpy>=2.3.5
Requires-Dist: pytest>=9.0.2
Requires-Dist: omegaconf>=2.3.0
Requires-Dist: loguru>=0.7.3
Requires-Dist: wandb>=0.23.1
Requires-Dist: pandas>=2.3.3
Requires-Dist: pre-commit>=4.5.1
Requires-Dist: tqdm>=4.67.1
Requires-Dist: ruff>=0.14.9
Requires-Dist: ty>=0.0.3
